{"metadata": {"dbt_schema_version": "https://schemas.getdbt.com/dbt/run-results/v5.json", "dbt_version": "1.7.1", "generated_at": "2023-11-10T00:11:13.332220Z", "invocation_id": "bb6ae1e5-0ce3-4d15-8465-79d241cb0270", "env": {}}, "results": [{"status": "success", "timing": [{"name": "compile", "started_at": "2023-11-10T00:11:12.595187Z", "completed_at": "2023-11-10T00:11:12.603044Z"}, {"name": "execute", "started_at": "2023-11-10T00:11:12.606661Z", "completed_at": "2023-11-10T00:11:12.606676Z"}], "thread_id": "Thread-2 (worker)", "execution_time": 0.026955127716064453, "adapter_response": {}, "message": null, "failures": null, "unique_id": "operation.dbt_constraints.dbt_constraints-on-run-end-0", "compiled": true, "compiled_code": "", "relation_name": null}, {"status": "success", "timing": [{"name": "compile", "started_at": "2023-11-10T00:11:12.584978Z", "completed_at": "2023-11-10T00:11:13.225840Z"}, {"name": "execute", "started_at": "2023-11-10T00:11:13.227703Z", "completed_at": "2023-11-10T00:11:13.227716Z"}], "thread_id": "Thread-1 (worker)", "execution_time": 0.7466824054718018, "adapter_response": {}, "message": null, "failures": null, "unique_id": "model.mcb_dbt.sample_model", "compiled": true, "compiled_code": "\n\n  SELECT\n'2023-11-09 16:11:13.056000-08:00' AS EXECUTED_TIMESTAMP,\n'To Test macros' AS LOG_MESSAGE", "relation_name": "DW_DEV_INGEST.public.sample_model"}], "elapsed_time": 1.6247851848602295, "args": {"exclude": [], "log_level_file": "debug", "partial_parse": true, "printer_width": 80, "defer": false, "static_parser": true, "use_colors_file": true, "select": [], "log_level": "info", "invocation_command": "dbt docs generate --target dev", "compile": true, "show_resource_report": false, "send_anonymous_usage_stats": false, "enable_legacy_logger": false, "which": "generate", "log_file_max_bytes": 10485760, "cache_selected_only": false, "macro_debugging": false, "introspect": true, "indirect_selection": "eager", "populate_cache": true, "project_dir": "/home/runner/work/mcb-dbt/mcb-dbt", "warn_error_options": {"include": [], "exclude": []}, "partial_parse_file_diff": true, "use_colors": true, "log_path": "/home/runner/work/mcb-dbt/mcb-dbt/logs", "quiet": false, "write_json": true, "profiles_dir": "/home/runner/work/mcb-dbt/mcb-dbt", "static": false, "log_format_file": "debug", "strict_mode": false, "favor_state": false, "target": "dev", "print": true, "version_check": true, "vars": {}, "empty_catalog": false, "log_format": "default"}}